gFunctionLibrary/__init__.py
gFunctionLibrary/access.py
gFunctionLibrary/coordinate_generator.py
gFunctionLibrary/featurerecognition.py
gFunctionLibrary/fileio.py
gFunctionLibrary/folder_to_lib.py
gFunctionLibrary/handle_contents.py
gFunctionLibrary/platform_specific.py
gFunctionLibrary/statistics.py
gFunctionLibrary/Libraries/Open_configurations_5m.json
gFunctionLibrary/Libraries/U_configurations_5m.json
gFunctionLibrary/Libraries/rectangle_5m.json
gFunctionLibrary/Libraries/zoned_rectangle_5m.json
gFunctionLibrary/UniformConfigurations/UniformConfigurations/Batch_Gen.py
gFunctionLibrary/UniformConfigurations/UniformConfigurations/Gen_Field.py
gFunctionLibrary/UniformConfigurations/UniformConfigurations/__init__.py
gFunctionLibrary/UniformConfigurations/UniformConfigurations/system.py
gFunctionLibrary-0.1.14.dist-info/LICENSE
gFunctionLibrary-0.1.14.dist-info/METADATA
gFunctionLibrary-0.1.14.dist-info/WHEEL
gFunctionLibrary-0.1.14.dist-info/top_level.txt
gFunctionLibrary-0.1.14.dist-info/RECORD
